WT_2/__init__.py
WT_2/database_builder.py
WT_2/hrms1.py
WT_2/msp_processor.py
WT_2/multiprocessing_manager.py
WT_2/peak_processor.py
WT_2/remove_duplicate.py
WT_2/sample_quantity.py
WT_2/samplealigment.py
WT_2/utils.py
WT_2/models/__init__.py
WT_2/models/HrMs1/__init__.py
WT_2/models/HrMs1/data_loader.py
WT_2/models/HrMs1/dataprepare.py
WT_2/models/HrMs1/model.py
WT_2/models/HrMs1/trainer_model.py
WT_2/models/Samplealignment/__init__.py
WT_2/models/Samplealignment/data_prepare.py
WT_2/models/Samplealignment/dataset.py
WT_2/models/Samplealignment/model.py
wt_2-0.5.dist-info/METADATA
wt_2-0.5.dist-info/WHEEL
wt_2-0.5.dist-info/top_level.txt
wt_2-0.5.dist-info/RECORD
